<annotation>
	<folder>images</folder>
	<filename>120.jpg</filename>
	<path>/home/yuyu/workspace/env/yolov5/VOCData/images/120.jpg</path>
	<source>
		<database>Unknown</database>
	</source>
	<size>
		<width>1280</width>
		<height>720</height>
		<depth>3</depth>
	</size>
	<segmented>0</segmented>
	<object>
		<name>purple</name>
		<pose>Unspecified</pose>
		<truncated>0</truncated>
		<difficult>0</difficult>
		<bndbox>
			<xmin>681</xmin>
			<ymin>215</ymin>
			<xmax>701</xmax>
			<ymax>234</ymax>
		</bndbox>
	</object>
	<object>
		<name>purple</name>
		<pose>Unspecified</pose>
		<truncated>0</truncated>
		<difficult>0</difficult>
		<bndbox>
			<xmin>362</xmin>
			<ymin>198</ymin>
			<xmax>387</xmax>
			<ymax>221</ymax>
		</bndbox>
	</object>
	<object>
		<name>purple</name>
		<pose>Unspecified</pose>
		<truncated>0</truncated>
		<difficult>0</difficult>
		<bndbox>
			<xmin>464</xmin>
			<ymin>209</ymin>
			<xmax>491</xmax>
			<ymax>235</ymax>
		</bndbox>
	</object>
	<object>
		<name>purple</name>
		<pose>Unspecified</pose>
		<truncated>0</truncated>
		<difficult>0</difficult>
		<bndbox>
			<xmin>133</xmin>
			<ymin>245</ymin>
			<xmax>180</xmax>
			<ymax>282</ymax>
		</bndbox>
	</object>
	<object>
		<name>purple</name>
		<pose>Unspecified</pose>
		<truncated>0</truncated>
		<difficult>0</difficult>
		<bndbox>
			<xmin>233</xmin>
			<ymin>237</ymin>
			<xmax>273</xmax>
			<ymax>266</ymax>
		</bndbox>
	</object>
	<object>
		<name>purple</name>
		<pose>Unspecified</pose>
		<truncated>0</truncated>
		<difficult>0</difficult>
		<bndbox>
			<xmin>289</xmin>
			<ymin>227</ymin>
			<xmax>325</xmax>
			<ymax>259</ymax>
		</bndbox>
	</object>
	<object>
		<name>purple</name>
		<pose>Unspecified</pose>
		<truncated>0</truncated>
		<difficult>0</difficult>
		<bndbox>
			<xmin>300</xmin>
			<ymin>237</ymin>
			<xmax>337</xmax>
			<ymax>269</ymax>
		</bndbox>
	</object>
	<object>
		<name>blue</name>
		<pose>Unspecified</pose>
		<truncated>0</truncated>
		<difficult>0</difficult>
		<bndbox>
			<xmin>74</xmin>
			<ymin>231</ymin>
			<xmax>118</xmax>
			<ymax>265</ymax>
		</bndbox>
	</object>
	<object>
		<name>blue</name>
		<pose>Unspecified</pose>
		<truncated>0</truncated>
		<difficult>0</difficult>
		<bndbox>
			<xmin>192</xmin>
			<ymin>196</ymin>
			<xmax>221</xmax>
			<ymax>221</ymax>
		</bndbox>
	</object>
	<object>
		<name>blue</name>
		<pose>Unspecified</pose>
		<truncated>0</truncated>
		<difficult>0</difficult>
		<bndbox>
			<xmin>241</xmin>
			<ymin>183</ymin>
			<xmax>267</xmax>
			<ymax>206</ymax>
		</bndbox>
	</object>
	<object>
		<name>blue</name>
		<pose>Unspecified</pose>
		<truncated>0</truncated>
		<difficult>0</difficult>
		<bndbox>
			<xmin>258</xmin>
			<ymin>199</ymin>
			<xmax>288</xmax>
			<ymax>225</ymax>
		</bndbox>
	</object>
	<object>
		<name>blue</name>
		<pose>Unspecified</pose>
		<truncated>0</truncated>
		<difficult>0</difficult>
		<bndbox>
			<xmin>256</xmin>
			<ymin>229</ymin>
			<xmax>286</xmax>
			<ymax>256</ymax>
		</bndbox>
	</object>
	<object>
		<name>blue</name>
		<pose>Unspecified</pose>
		<truncated>0</truncated>
		<difficult>0</difficult>
		<bndbox>
			<xmin>406</xmin>
			<ymin>205</ymin>
			<xmax>431</xmax>
			<ymax>230</ymax>
		</bndbox>
	</object>
</annotation>
