<annotation>
	<folder>304_632</folder>
	<filename>403.jpg</filename>
	<path>/home/ali/下载/304_632/403.jpg</path>
	<source>
		<database>Unknown</database>
	</source>
	<size>
		<width>1280</width>
		<height>720</height>
		<depth>3</depth>
	</size>
	<segmented>0</segmented>
	<object>
		<name>red</name>
		<pose>Unspecified</pose>
		<truncated>0</truncated>
		<difficult>0</difficult>
		<bndbox>
			<xmin>502</xmin>
			<ymin>152</ymin>
			<xmax>548</xmax>
			<ymax>198</ymax>
		</bndbox>
	</object>
	<object>
		<name>red</name>
		<pose>Unspecified</pose>
		<truncated>0</truncated>
		<difficult>0</difficult>
		<bndbox>
			<xmin>1043</xmin>
			<ymin>139</ymin>
			<xmax>1117</xmax>
			<ymax>200</ymax>
		</bndbox>
	</object>
	<object>
		<name>red</name>
		<pose>Unspecified</pose>
		<truncated>0</truncated>
		<difficult>0</difficult>
		<bndbox>
			<xmin>1121</xmin>
			<ymin>81</ymin>
			<xmax>1178</xmax>
			<ymax>133</ymax>
		</bndbox>
	</object>
	<object>
		<name>red</name>
		<pose>Unspecified</pose>
		<truncated>1</truncated>
		<difficult>0</difficult>
		<bndbox>
			<xmin>1</xmin>
			<ymin>472</ymin>
			<xmax>43</xmax>
			<ymax>523</ymax>
		</bndbox>
	</object>
	<object>
		<name>red</name>
		<pose>Unspecified</pose>
		<truncated>0</truncated>
		<difficult>0</difficult>
		<bndbox>
			<xmin>229</xmin>
			<ymin>184</ymin>
			<xmax>267</xmax>
			<ymax>218</ymax>
		</bndbox>
	</object>
	<object>
		<name>red</name>
		<pose>Unspecified</pose>
		<truncated>0</truncated>
		<difficult>0</difficult>
		<bndbox>
			<xmin>255</xmin>
			<ymin>168</ymin>
			<xmax>294</xmax>
			<ymax>196</ymax>
		</bndbox>
	</object>
	<object>
		<name>purple</name>
		<pose>Unspecified</pose>
		<truncated>0</truncated>
		<difficult>0</difficult>
		<bndbox>
			<xmin>139</xmin>
			<ymin>232</ymin>
			<xmax>186</xmax>
			<ymax>267</ymax>
		</bndbox>
	</object>
	<object>
		<name>purple</name>
		<pose>Unspecified</pose>
		<truncated>0</truncated>
		<difficult>0</difficult>
		<bndbox>
			<xmin>328</xmin>
			<ymin>218</ymin>
			<xmax>377</xmax>
			<ymax>264</ymax>
		</bndbox>
	</object>
	<object>
		<name>purple</name>
		<pose>Unspecified</pose>
		<truncated>0</truncated>
		<difficult>0</difficult>
		<bndbox>
			<xmin>346</xmin>
			<ymin>234</ymin>
			<xmax>405</xmax>
			<ymax>280</ymax>
		</bndbox>
	</object>
	<object>
		<name>purple</name>
		<pose>Unspecified</pose>
		<truncated>0</truncated>
		<difficult>0</difficult>
		<bndbox>
			<xmin>412</xmin>
			<ymin>204</ymin>
			<xmax>462</xmax>
			<ymax>248</ymax>
		</bndbox>
	</object>
</annotation>
